cjm_fasthtml_plugins/__init__.py
cjm_fasthtml_plugins/_modidx.py
cjm_fasthtml_plugins/core/__init__.py
cjm_fasthtml_plugins/core/execution_mode.py
cjm_fasthtml_plugins/core/metadata.py
cjm_fasthtml_plugins/core/registry.py
cjm_fasthtml_plugins/protocols/__init__.py
cjm_fasthtml_plugins/protocols/cloud_aware.py
cjm_fasthtml_plugins/protocols/lifecycle.py
cjm_fasthtml_plugins/utils/__init__.py
cjm_fasthtml_plugins/utils/helpers.py
cjm_fasthtml_plugins-0.0.2.dist-info/licenses/LICENSE
cjm_fasthtml_plugins-0.0.2.dist-info/METADATA
cjm_fasthtml_plugins-0.0.2.dist-info/WHEEL
cjm_fasthtml_plugins-0.0.2.dist-info/entry_points.txt
cjm_fasthtml_plugins-0.0.2.dist-info/top_level.txt
cjm_fasthtml_plugins-0.0.2.dist-info/RECORD
